[
  {
    "id": "ep3",
    "title": "Episode Three",
    "date": "2025-06-03",
    "image": "episodes/ep3/image.png",
    "text": "episodes/ep3/text.md",
    "audio": "episodes/ep3/audio.mp3",
    "textUpdated": 1780774868864.1511,
    "imageUpdated": 1780770189725.8965,
    "audioUpdated": 1780777503781.1104,
    "voice": "male",
    "timing": "episodes/ep3/timing.json",
    "timingUpdated": 1780778098646.6738
  },
  {
    "id": "ep2",
    "title": "Episode Two",
    "date": "2025-06-02",
    "image": "episodes/ep2/image.png",
    "text": "episodes/ep2/text.md",
    "audio": "episodes/ep2/audio.mp3",
    "textUpdated": 1780774758522.8533,
    "imageUpdated": 1780770189657.576,
    "audioUpdated": 1780777180373.5837,
    "voice": "female",
    "timing": "episodes/ep2/timing.json",
    "timingUpdated": 1780778095358.3896
  },
  {
    "id": "ep1",
    "title": "Episode One",
    "date": "2025-06-01",
    "image": "episodes/ep1/image.png",
    "text": "episodes/ep1/text.md",
    "audio": "episodes/ep1/audio.mp3",
    "textUpdated": 1780774764798.2634,
    "imageUpdated": 1780770189585.6885,
    "audioUpdated": 1780777590216.083,
    "voice": "male",
    "timing": "episodes/ep1/timing.json",
    "timingUpdated": 1780778089633.4797
  }
]
